kson/__init__.py
kson/decoder.py
kson/encoder.py
kson/exceptions.py
kson_irs-0.0.2.dist-info/LICENSE
kson_irs-0.0.2.dist-info/METADATA
kson_irs-0.0.2.dist-info/WHEEL
kson_irs-0.0.2.dist-info/top_level.txt
kson_irs-0.0.2.dist-info/RECORD
