Metadata-Version: 2.1
Name: kson-irs
Version: 0.0.2
Summary: Python Library for Nobly-Flavoured JSON
Author-email: Dutchess_of_Kure <illinirhythmsyndicate@gmail.com>
Project-URL: Homepage, https://github.com/orgs/Illini-Rhythm-Syndicate/kson
Project-URL: Issues, https://github.com/orgs/Illini-Rhythm-Syndicate/kson/issues
Classifier: Programming Language :: Python :: 3
Classifier: License :: OSI Approved :: MIT License
Classifier: Operating System :: OS Independent
Requires-Python: >=3.8
License-File: LICENSE
